{
  "project_info": {
    "project_number": "419891757950",
    "firebase_url": "https://geotoll-d5f56.firebaseio.com",
    "project_id": "geotoll-d5f56",
    "storage_bucket": "geotoll-d5f56.appspot.com"
  },
  "client": [
    {
      "client_info": {
        "mobilesdk_app_id": "1:419891757950:android:c50bd7ec84421f36",
        "android_client_info": {
          "package_name": "com.example.saifil.geotoll"
        }
      },
      "oauth_client": [
        {
          "client_id": "419891757950-5ht5qg5vpe9mv1fv0h70fpfsabr1b8lf.apps.googleusercontent.com",
          "client_type": 1,
          "android_info": {
            "package_name": "com.example.saifil.geotoll",
            "certificate_hash": "b0f7df882ed6ffc08464bbfb2613f9a3243c9912"
          }
        },
        {
          "client_id": "419891757950-n341ai8km8848d89s5i1jntjme7nugke.apps.googleusercontent.com",
          "client_type": 3
        }
      ],
      "api_key": [
        {
          "current_key": "AIzaSyBwzm_JA_csU7oTorD39TSDnP5PwDJBhT8"
        }
      ],
      "services": {
        "analytics_service": {
          "status": 1
        },
        "appinvite_service": {
          "status": 2,
          "other_platform_oauth_client": [
            {
              "client_id": "419891757950-n341ai8km8848d89s5i1jntjme7nugke.apps.googleusercontent.com",
              "client_type": 3
            }
          ]
        },
        "ads_service": {
          "status": 2
        }
      }
    }
  ],
  "configuration_version": "1"
}